[
  {
    "id": "2dddb787-6cba-457b-b0ce-2aba32744d49",
    "user_id": "fff13d7a-6b26-454e-9b6a-f7b5c469574d",
    "movie_id": "movie-3",
    "movie_title": "The Batman",
    "showtime": "7:00 PM",
    "seats": [
      "A4",
      "B4",
      "B5",
      "A5"
    ],
    "total_price": 48.0,
    "booking_date": "2025-09-29T19:38:49.887943",
    "status": "cancelled"
  },
  {
    "id": "62ab519c-6404-47a8-abf6-c1b38cc2c990",
    "user_id": "test-user-123",
    "movie_id": "movie-1",
    "movie_title": "Avengers: Endgame",
    "showtime": "7:00 PM",
    "seats": [
      "A1",
      "A2"
    ],
    "total_price": 24.0,
    "booking_date": "2025-09-29T22:26:46.935430",
    "status": "cancelled"
  },
  {
    "id": "3d0f4513-0beb-43c2-8e34-3a1048545b99",
    "user_id": "test-user-123",
    "movie_id": "movie-1",
    "movie_title": "Avengers: Endgame",
    "showtime": "7:00 PM",
    "seats": [
      "A3",
      "A4"
    ],
    "total_price": 24.0,
    "booking_date": "2025-09-29T22:27:33.947627",
    "status": "confirmed"
  },
  {
    "id": "9efcadb9-2b21-441b-a8cb-1c450a9165f6",
    "user_id": "test-user-123",
    "movie_id": "movie-1",
    "movie_title": "Avengers: Endgame",
    "showtime": "7:00 PM",
    "seats": [
      "A5",
      "A6"
    ],
    "total_price": 24.0,
    "booking_date": "2025-09-29T22:28:16.763746",
    "status": "confirmed"
  },
  {
    "id": "38ff2971-1bf9-4b75-8dab-398921b41fa7",
    "user_id": "test-user-123",
    "movie_id": "movie-1",
    "movie_title": "Avengers: Endgame",
    "showtime": "7:00 PM",
    "seats": [],
    "total_price": 0.0,
    "booking_date": "2025-09-29T22:35:33.345681",
    "status": "cancelled"
  },
  {
    "id": "0bf22aef-e9e2-4c76-b9f7-4c7ae901abd1",
    "user_id": "7a4396b2-4c6b-45db-a995-fafdb0d9aee6",
    "movie_id": "movie-1",
    "movie_title": "Avengers: Endgame",
    "showtime": "7:00 PM",
    "seats": [
      "A995",
      "B2",
      "C6",
      "A4396",
      "D9",
      "E6",
      "B0"
    ],
    "total_price": 84.0,
    "booking_date": "2025-09-29T23:05:43.262640",
    "status": "confirmed"
  },
  {
    "id": "d6202b90-8ad2-4a83-b917-e8b0c8406a8d",
    "user_id": "7a4396b2-4c6b-45db-a995-fafdb0d9aee6",
    "movie_id": "movie-1",
    "movie_title": "Avengers: Endgame",
    "showtime": "7:00 PM",
    "seats": [
      "C1",
      "C2"
    ],
    "total_price": 24.0,
    "booking_date": "2025-10-01T14:11:08.845157",
    "status": "confirmed"
  },
  {
    "id": "6ed3e7c7-86ec-4e10-889c-a33736d665cb",
    "user_id": "5bc2b6c9-12b5-413d-82db-eb9baf09afe1",
    "movie_id": "movie-4",
    "movie_title": "Dune",
    "showtime": "7:00 PM",
    "seats": [
      "A1",
      "A2"
    ],
    "total_price": 24.0,
    "booking_date": "2026-05-31T20:03:33.425065",
    "status": "cancelled"
  },
  {
    "id": "8a165656-e9af-46c8-bd51-1565ee24a95b",
    "user_id": "5bc2b6c9-12b5-413d-82db-eb9baf09afe1",
    "movie_id": "movie-2",
    "movie_title": "Spider-Man: No Way Home",
    "showtime": "10:00 AM",
    "seats": [
      "C3",
      "C4"
    ],
    "total_price": 24.0,
    "booking_date": "2026-05-31T20:15:18.819333",
    "status": "confirmed"
  },
  {
    "id": "1996c455-aa85-43b3-94c9-742455f1413f",
    "user_id": "13d87fcc-62b5-4a29-b757-e98692a31e17",
    "movie_id": "movie-2",
    "movie_title": "Spider-Man: No Way Home",
    "showtime": "10:00 AM",
    "seats": [
      "C6"
    ],
    "total_price": 12.0,
    "booking_date": "2026-05-31T20:21:20.987396",
    "status": "confirmed"
  },
  {
    "id": "75155e99-bf03-4aef-a30b-2e6a4ee35703",
    "user_id": "5bc2b6c9-12b5-413d-82db-eb9baf09afe1",
    "movie_id": "movie-2",
    "movie_title": "Spider-Man: No Way Home",
    "showtime": "10:00 AM",
    "seats": [
      "A1",
      "A2"
    ],
    "total_price": 24.0,
    "booking_date": "2026-05-31T20:24:50.442372",
    "status": "confirmed"
  }
]